assisted_service_client/__init__.py
assisted_service_client/api_client.py
assisted_service_client/configuration.py
assisted_service_client/rest.py
assisted_service_client/api/__init__.py
assisted_service_client/api/events_api.py
assisted_service_client/api/installer_api.py
assisted_service_client/api/managed_domains_api.py
assisted_service_client/api/manifests_api.py
assisted_service_client/api/operators_api.py
assisted_service_client/api/versions_api.py
assisted_service_client/models/__init__.py
assisted_service_client/models/api_vip.py
assisted_service_client/models/api_vip_connectivity_additional_request_header.py
assisted_service_client/models/api_vip_connectivity_request.py
assisted_service_client/models/api_vip_connectivity_response.py
assisted_service_client/models/architecture_support_level_id.py
assisted_service_client/models/bind_host_params.py
assisted_service_client/models/boot.py
assisted_service_client/models/bundle.py
assisted_service_client/models/cluster.py
assisted_service_client/models/cluster_create_params.py
assisted_service_client/models/cluster_default_config.py
assisted_service_client/models/cluster_finalizing_progress.py
assisted_service_client/models/cluster_host_requirements.py
assisted_service_client/models/cluster_host_requirements_details.py
assisted_service_client/models/cluster_host_requirements_list.py
assisted_service_client/models/cluster_list.py
assisted_service_client/models/cluster_network.py
assisted_service_client/models/cluster_progress_info.py
assisted_service_client/models/cluster_validation_id.py
assisted_service_client/models/completion_params.py
assisted_service_client/models/connectivity_check_host.py
assisted_service_client/models/connectivity_check_nic.py
assisted_service_client/models/connectivity_check_params.py
assisted_service_client/models/connectivity_remote_host.py
assisted_service_client/models/connectivity_report.py
assisted_service_client/models/container_image_availability.py
assisted_service_client-2.50.0.post6.dist-info/METADATA
assisted_service_client-2.50.0.post6.dist-info/WHEEL
assisted_service_client-2.50.0.post6.dist-info/top_level.txt
assisted_service_client-2.50.0.post6.dist-info/RECORD
